scikit_criteria-0.9.dist-info/licenses/LICENSE.txt
skcriteria/__init__.py
skcriteria/extend.py
skcriteria/madm.py
skcriteria/pipeline.py
skcriteria/testing.py
skcriteria/tiebreaker.py
skcriteria/agg/__init__.py
skcriteria/agg/_agg_base.py
skcriteria/agg/aras.py
skcriteria/agg/cocoso.py
skcriteria/agg/codas.py
skcriteria/agg/copras.py
skcriteria/agg/edas.py
skcriteria/agg/electre.py
skcriteria/agg/ervd.py
skcriteria/agg/mabac.py
skcriteria/agg/moora.py
skcriteria/agg/ocra.py
skcriteria/agg/probid.py
skcriteria/agg/ram.py
skcriteria/agg/rim.py
skcriteria/agg/similarity.py
skcriteria/agg/simple.py
skcriteria/agg/simus.py
skcriteria/agg/spotis.py
skcriteria/agg/topsis.py
skcriteria/agg/vikor.py
skcriteria/agg/waspas.py
skcriteria/cmp/__init__.py
skcriteria/cmp/ranks_cmp.py
skcriteria/cmp/ranks_rev/__init__.py
skcriteria/cmp/ranks_rev/rank_inv_check.py
skcriteria/core/__init__.py
skcriteria/core/data.py
skcriteria/core/dominance.py
skcriteria/core/methods.py
skcriteria/core/objectives.py
skcriteria/core/plot.py
skcriteria/core/stats.py
skcriteria/datasets/__init__.py
skcriteria/datasets/van2021evaluation/windows_size_15.dmsy
skcriteria/datasets/van2021evaluation/windows_size_7.dmsy
skcriteria/io/__init__.py
skcriteria/io/dmsy.py
skcriteria/pipelines/__init__.py
skcriteria/pipelines/combinatorial.py
skcriteria/pipelines/simple_pipeline.py
skcriteria/preprocessing/__init__.py
skcriteria/preprocessing/_preprocessing_base.py
skcriteria/preprocessing/distance.py
skcriteria/preprocessing/filters.py
skcriteria/preprocessing/impute.py
skcriteria/preprocessing/increment.py
skcriteria/preprocessing/invert_objectives.py
skcriteria/preprocessing/push_negatives.py
skcriteria/preprocessing/scalers.py
skcriteria/preprocessing/weighters.py
skcriteria/ranksrev/__init__.py
skcriteria/ranksrev/rank_invariant_check.py
skcriteria/ranksrev/rank_transitivity_check.py
skcriteria/utils/__init__.py
skcriteria/utils/accabc.py
skcriteria/utils/bunch.py
skcriteria/utils/cmanagers.py
skcriteria/utils/cycle_removal.py
skcriteria/utils/deprecate.py
scikit_criteria-0.9.dist-info/METADATA
scikit_criteria-0.9.dist-info/WHEEL
scikit_criteria-0.9.dist-info/top_level.txt
scikit_criteria-0.9.dist-info/RECORD
