Metadata-Version: 2.4
Name: scikit-criteria
Version: 0.9
Summary: Scikit-Criteria is a collections of algorithms, methods and techniques for multiple-criteria decision analysis.
Author-email: Juan B Cabral & QuatroPe <jbcabral@unc.edu.ar>
License: Copyright (c) 2016-2021, Cabral, Juan; Luczywo, Nadia
Project-URL: Homepage, https://scikit-criteria.quatrope.org/
Project-URL: Repository, https://github.com/quatrope/scikit-criteria
Keywords: muticriteria,mcda,mcdm,weightedsum,weightedproduct,simus,topsis,moora,electre,probid,critic,entropy,dominance,packaging
Classifier: Development Status :: 4 - Beta
Classifier: Intended Audience :: Education
Classifier: Intended Audience :: Science/Research
Classifier: Operating System :: OS Independent
Classifier: Programming Language :: Python
Classifier: Programming Language :: Python :: 3
Classifier: Programming Language :: Python :: 3.9
Classifier: Programming Language :: Python :: 3.10
Classifier: Programming Language :: Python :: 3.11
Classifier: Programming Language :: Python :: 3.12
Classifier: Programming Language :: Python :: 3.13
Classifier: Programming Language :: Python :: Implementation :: CPython
Classifier: Topic :: Scientific/Engineering
License-File: LICENSE.txt
Requires-Dist: numpy>=2.0
Requires-Dist: networkx>=3.2
Requires-Dist: pandas>=2.0
Requires-Dist: scipy>=1.10
Requires-Dist: jinja2
Requires-Dist: custom_inherit
Requires-Dist: seaborn<0.14,>=0.13
Requires-Dist: pulp<2.9,>=2.8
Requires-Dist: Deprecated
Requires-Dist: scikit-learn>=1.6
Requires-Dist: matplotlib<3.9,>=3.8.2
Requires-Dist: methodtools
Requires-Dist: pyyaml>=6.0
Dynamic: license-file
